{
  "entries": [
    {
      "title": "Expense in the region of Mindanao Region",
      "content": [
        "The total expense per month in the Mindanao Region is ₱12,464.77"
      ],
      "author": "https://psa.gov.ph/statistics/income-expenditure/fies/node/1684059678"
    },
    {
      "title": "Expense in the region of Cordillera Administrative Region",
      "content": [
        "The total expense per month in the Cordillera Administrative Region is ₱20,250.79"
      ],
      "author": "https://psa.gov.ph/statistics/income-expenditure/fies/node/1684059678"
    },
    {
      "title": "Expense in the region of Caraga Region",
      "content": [
        "The total expense per month in the Caraga Region is ₱16,515.44"
      ],
      "author": "https://psa.gov.ph/statistics/income-expenditure/fies/node/1684059678"
    },
    {
      "title": "Expense in the region of Ilocos",
      "content": [
        "The total expense per month in the Ilocos Region is ₱17,468.90"
      ],
      "author": "https://psa.gov.ph/statistics/income-expenditure/fies/node/1684059678"
    },
    {
      "title": "Expense in the region of Cagayan Valley",
      "content": [
        "The total expense per month in the Cagayan Valley is ₱16,783.28"
      ],
      "author": "https://psa.gov.ph/statistics/income-expenditure/fies/node/1684059678"
    },
    {
      "title": "Expense in the region of Central Luzon",
      "content": [
        "The total expense per month in the Central Luzon is ₱21,530.39"
      ],
      "author": "https://psa.gov.ph/statistics/income-expenditure/fies/node/1684059678"
    },
    {
      "title": "Expense in the region of Calabarzon",
      "content": [
        "The total expense per month in the Calabarzon is ₱23,381.04"
      ],
      "author": "https://psa.gov.ph/statistics/income-expenditure/fies/node/1684059678"
    },
    {
      "title": "Expense in the region of Mimaropa Region",
      "content": [
        "The total expense per month in the Mimaropa Region is ₱14,846.20"
      ],
      "author": "https://psa.gov.ph/statistics/income-expenditure/fies/node/1684059678"
    },
    {
      "title": "Expense in the region of Zamboanga Peninsula",
      "content": [
        "The total expense per month in the Zamboanga Peninsula is ₱13,844.95"
      ],
      "author": "https://psa.gov.ph/statistics/income-expenditure/fies/node/1684059678"
    },
    {
      "title": "Expense in the region of National Capital Region",
      "content": [
        "The total expense per month in the National Capital Region is ₱26,803.84"
      ],
      "author": "https://psa.gov.ph/statistics/income-expenditure/fies/node/1684059678"
    },
    {
      "title": "Expense in the region of Bicol Region",
      "content": [
        "The total expense per month in the Bicol Region is ₱15,864.26"
      ],
      "author": "https://psa.gov.ph/statistics/income-expenditure/fies/node/1684059678"
    },
    {
      "title": "Expense in the region of Western Visayas",
      "content": [
        "The total expense per month in the Western Visayas is ₱16,643.89"
      ],
      "author": "https://psa.gov.ph/statistics/income-expenditure/fies/node/1684059678"
    },
    {
      "title": "Expense in the region of Central Visayas",
      "content": [
        "The total expense per month in the Central Visayas is ₱16,139.76"
      ],
      "author": "https://psa.gov.ph/statistics/income-expenditure/fies/node/1684059678"
    },
    {
      "title": "Expense in the region of Eastern Visayas",
      "content": [
        "The total expense per month in the Eastern Visayas is ₱15,764.22"
      ],
      "author": "https://psa.gov.ph/statistics/income-expenditure/fies/node/1684059678"
    },
    {
      "title": "Expense in the region of Northern Mindanao",
      "content": [
        "The total expense per month in the Northern Mindanao is ₱14,636.76"
      ],
      "author": "https://psa.gov.ph/statistics/income-expenditure/fies/node/1684059678"
    },
    {
      "title": "Expense in the region of Davao Region",
      "content": [
        "The total expense per month in the Davao Region is ₱15,320.38"
      ],
      "author": "https://psa.gov.ph/statistics/income-expenditure/fies/node/1684059678"
    },
    {
      "title": "Expense in the region of Soccsksargen",
      "content": [
        "The total expense per month in the Soccsksargen is ₱14,533.97"
      ],
      "author": "https://psa.gov.ph/statistics/income-expenditure/fies/node/1684059678"
    }
  ]
}
